manim_mobject_svg/__init__.py
manim_mobject_svg/svg.py
manim_mobject_svg-0.5.0.dist-info/LICENSE
manim_mobject_svg-0.5.0.dist-info/METADATA
manim_mobject_svg-0.5.0.dist-info/WHEEL
manim_mobject_svg-0.5.0.dist-info/entry_points.txt
manim_mobject_svg-0.5.0.dist-info/RECORD
