Metadata-Version: 2.1
Name: manim-mobject-svg
Version: 0.5.0
Summary: Create SVG files from VMobject and VGroup in Manim
Home-page: https://github.com/naveen521kk/manim-mobject-svg
License: MIT
Author: Naveen M K
Author-email: naveen521kk@gmail.com
Requires-Python: >=3.9,<3.13
Classifier: License :: OSI Approved :: MIT License
Classifier: Programming Language :: Python :: 3
Classifier: Programming Language :: Python :: 3.9
Classifier: Programming Language :: Python :: 3.10
Classifier: Programming Language :: Python :: 3.11
Classifier: Programming Language :: Python :: 3.12
Requires-Dist: manim (>=0.16.0)
Requires-Dist: pycairo (>=1,<2)
Project-URL: Repository, https://github.com/naveen521kk/manim-mobject-svg
